Workbook

Sheet Risk Register
A1: Risk Register
A2: Cyber, Operational & Compliance Risk Portfolio — Enterprise Risk Register
A4: ID | B4: Risk Description | C4: Category | D4: Likelihood | E4: Impact | F4: Inherent Rating | G4: Existing Controls | H4: Treatment Plan | I4: Treatment Type | J4: Owner | K4: Residual Likelihood | L4: Residual Impact | M4: Residual Rating | N4: Target Date | O4: Inherent Band | P4: Residual Band | Q4: Residual Rank
A5: R01 | B5: Phishing attack leads to compromised employee credentials, enabling unauthorised system access. | C5: Cyber | D5: 4 | E5: 4 | F5: =D5*E5 -> 16 | G5: C01, C02 | H5: Roll out mandatory quarterly phishing simulations; enforce MFA on all cloud and email accounts. | I5: Treat | J5: Head of IT Security | K5: 2 | L5: 3 | M5: =K5*L5 -> 6 | N5: 2026-11-30 | O5: =IF(F5<=5,"Low",IF(F5<=10,"Medium",IF(F5<=15,"High","Critical"))) -> Critical | P5: =IF(M5<=6,"Low",IF(M5<=12,"Medium","High")) -> Low | Q5: =RANK(M5,$M$5:$M$19,0)+COUNTIF($M$5:M5,M5)-1 -> 2
A6: R02 | B6: Ransomware infection encrypts production systems, halting business operations. | C6: Cyber | D6: 3 | E6: 5 | F6: =D6*E6 -> 15 | G6: C02, C03, C10 | H6: Deploy EDR across all endpoints; validate immutable, offline backups with quarterly restore tests. | I6: Treat | J6: Head of IT Security | K6: 2 | L6: 4 | M6: =K6*L6 -> 8 | N6: 2026-12-15 | O6: =IF(F6<=6,"Low",IF(F6<=12,"Medium","High")) -> High | P6: =IF(M6<=6,"Low",IF(M6<=12,"Medium","High")) -> Medium | Q6: =RANK(M6,$M$5:$M$19,0)+COUNTIF($M$5:M6,M6)-1 -> 1
A7: R03 | B7: Unpatched critical vulnerabilities on internet-facing systems are exploited by threat actors. | C7: Cyber | D7: 3 | E7: 4 | F7: =D7*E7 -> 12 | G7: C04 | H7: Implement 14-day SLA for critical patches; add continuous external vulnerability scanning. | I7: Treat | J7: IT Infrastructure Manager | K7: 2 | L7: 3 | M7: =K7*L7 -> 6 | N7: 2026-11-15 | O7: =IF(F7<=6,"Low",IF(F7<=12,"Medium","High")) -> Medium | P7: =IF(M7<=6,"Low",IF(M7<=12,"Medium","High")) -> Low | Q7: =RANK(M7,$M$5:$M$19,0)+COUNTIF($M$5:M7,M7)-1 -> 3
A8: R04 | B8: Malicious or negligent insider exfiltrates sensitive customer or financial data. | C8: Cyber | D8: 2 | E8: 5 | F8: =D8*E8 -> 10 | G8: C05, C11 | H8: Deploy DLP on email and endpoints; enforce least-privilege access reviews every 6 months. | I8: Treat | J8: Head of IT Security | K8: 1 | L8: 4 | M8: =K8*L8 -> 4 | N8: 2027-01-31 | O8: =IF(F8<=6,"Low",IF(F8<=12,"Medium","High")) -> Medium | P8: =IF(M8<=6,"Low",IF(M8<=12,"Medium","High")) -> Low | Q8: =RANK(M8,$M$5:$M$19,0)+COUNTIF($M$5:M8,M8)-1 -> 5
A9: R05 | B9: Cloud storage misconfiguration exposes sensitive data to the public internet. | C9: Cyber | D9: 3 | E9: 4 | F9: =D9*E9 -> 12 | G9: C06 | H9: Enable CSPM tooling with automated alerts and remediation playbooks for public storage exposure. | I9: Treat | J9: Cloud Platform Owner | K9: 1 | L9: 4 | M9: =K9*L9 -> 4 | N9: 2026-10-31 | O9: =IF(F9<=6,"Low",IF(F9<=12,"Medium","High")) -> Medium | P9: =IF(M9<=6,"Low",IF(M9<=12,"Medium","High")) -> Low | Q9: =RANK(M9,$M$5:$M$19,0)+COUNTIF($M$5:M9,M9)-1 -> 6
A10: R06 | B10: Loss of key personnel results in loss of critical operational or technical knowledge. | C10: Operational | D10: 3 | E10: 3 | F10: =D10*E10 -> 9 | G10: C07 | H10: Document critical processes; implement cross-training and formal succession plans for key roles. | I10: Treat | J10: Head of Operations | K10: 2 | L10: 2 | M10: =K10*L10 -> 4 | N10: 2027-02-28 | O10: =IF(F10<=6,"Low",IF(F10<=12,"Medium","High")) -> Medium | P10: =IF(M10<=6,"Low",IF(M10<=12,"Medium","High")) -> Low | Q10: =RANK(M10,$M$5:$M$19,0)+COUNTIF($M$5:M10,M10)-1 -> 7
A11: R07 | B11: Inadequate disaster recovery plan leads to extended downtime after a major incident. | C11: Operational | D11: 2 | E11: 5 | F11: =D11*E11 -> 10 | G11: C08, C10 | H11: Formalise and test DR plan annually; define and validate RTO/RPO targets with the business. | I11: Treat | J11: Head of IT Infrastructure | K11: 1 | L11: 4 | M11: =K11*L11 -> 4 | N11: 2027-03-31 | O11: =IF(F11<=6,"Low",IF(F11<=12,"Medium","High")) -> Medium | P11: =IF(M11<=6,"Low",IF(M11<=12,"Medium","High")) -> Low | Q11: =RANK(M11,$M$5:$M$19,0)+COUNTIF($M$5:M11,M11)-1 -> 8
A12: R08 | B12: Disruption at a single-source critical supplier halts a core business process. | C12: Operational | D12: 3 | E12: 4 | F12: =D12*E12 -> 12 | G12: C09 | H12: Identify and qualify secondary suppliers for critical inputs; build contingency stock where feasible. | I12: Treat | J12: Procurement Lead | K12: 2 | L12: 3 | M12: =K12*L12 -> 6 | N12: 2027-01-15 | O12: =IF(F12<=6,"Low",IF(F12<=12,"Medium","High")) -> Medium | P12: =IF(M12<=6,"Low",IF(M12<=12,"Medium","High")) -> Low | Q12: =RANK(M12,$M$5:$M$19,0)+COUNTIF($M$5:M12,M12)-1 -> 4
A13: R09 | B13: Inadequate backup procedures result in permanent loss of business-critical data. | C13: Operational | D13: 2 | E13: 4 | F13: =D13*E13 -> 8 | G13: C10 | H13: Automate daily backups with quarterly restore testing and offsite/immutable copies. | I13: Treat | J13: IT Infrastructure Manager | K13: 1 | L13: 3 | M13: =K13*L13 -> 3 | N13: 2026-11-30 | O13: =IF(F13<=6,"Low",IF(F13<=12,"Medium","High")) -> Medium | P13: =IF(M13<=6,"Low",IF(M13<=12,"Medium","High")) -> Low | Q13: =RANK(M13,$M$5:$M$19,0)+COUNTIF($M$5:M13,M13)-1 -> 12
A14: R10 | B14: Physical security breach at office or data centre leads to theft, damage, or unauthorised access. | C14: Operational | D14: 2 | E14: 3 | F14: =D14*E14 -> 6 | G14: C11 | H14: Upgrade badge access control and CCTV coverage; introduce formal visitor management process. | I14: Treat | J14: Facilities Manager | K14: 1 | L14: 2 | M14: =K14*L14 -> 2 | N14: 2027-02-15 | O14: =IF(F14<=6,"Low",IF(F14<=12,"Medium","High")) -> Low | P14: =IF(M14<=6,"Low",IF(M14<=12,"Medium","High")) -> Low | Q14: =RANK(M14,$M$5:$M$19,0)+COUNTIF($M$5:M14,M14)-1 -> 13
A15: R11 | B15: Non-compliance with GDPR / data protection requirements results in regulatory fines and reputational harm. | C15: Compliance | D15: 3 | E15: 5 | F15: =D15*E15 -> 15 | G15: C12, C14 | H15: Conduct DPIAs for all new processing activities; appoint DPO and run annual compliance audit. | I15: Treat | J15: Data Protection Officer | K15: 1 | L15: 4 | M15: =K15*L15 -> 4 | N15: 2026-12-31 | O15: =IF(F15<=6,"Low",IF(F15<=12,"Medium","High")) -> High | P15: =IF(M15<=6,"Low",IF(M15<=12,"Medium","High")) -> Low | Q15: =RANK(M15,$M$5:$M$19,0)+COUNTIF($M$5:M15,M15)-1 -> 9
A16: R12 | B16: Failure to meet industry regulatory reporting deadlines results in penalties or sanctions. | C16: Compliance | D16: 2 | E16: 3 | F16: =D16*E16 -> 6 | G16: C13 | H16: Implement a centralised compliance calendar with automated reminders and owner sign-off. | I16: Treat | J16: Compliance Manager | K16: 1 | L16: 2 | M16: =K16*L16 -> 2 | N16: 2026-10-31 | O16: =IF(F16<=6,"Low",IF(F16<=12,"Medium","High")) -> Low | P16: =IF(M16<=6,"Low",IF(M16<=12,"Medium","High")) -> Low | Q16: =RANK(M16,$M$5:$M$19,0)+COUNTIF($M$5:M16,M16)-1 -> 14
A17: R13 | B17: Inadequate records retention practices cause failure to produce records for e-discovery or audit. | C17: Compliance | D17: 2 | E17: 3 | F17: =D17*E17 -> 6 | G17: C14 | H17: Publish records retention and disposal schedule; train staff and audit compliance annually. | I17: Treat | J17: Compliance Manager | K17: 1 | L17: 2 | M17: =K17*L17 -> 2 | N17: 2027-01-31 | O17: =IF(F17<=6,"Low",IF(F17<=12,"Medium","High")) -> Low | P17: =IF(M17<=6,"Low",IF(M17<=12,"Medium","High")) -> Low | Q17: =RANK(M17,$M$5:$M$19,0)+COUNTIF($M$5:M17,M17)-1 -> 15
... A19: R15 | B19: Inadequate due diligence on third parties results in onboarding vendors with unacceptable risk exposure. | C19: Compliance | D19: 3 | E19: 3 | F19: =D19*E19 -> 9 | G19: C16 | H19: Mandate security and compliance questionnaires before onboarding; review high-risk vendors annually. | I19: Tolerate | J19: Procurement Lead | K19: 2 | L19: 2 | M19: =K19*L19 -> 4 | N19: 2027-04-30 | O19: =IF(F19<=6,"Low",IF(F19<=12,"Medium","High")) -> Medium | P19: =IF(M19<=6,"Low",IF(M19<=12,"Medium","High")) -> Low | Q19: =RANK(M19,$M$5:$M$19,0)+COUNTIF($M$5:M19,M19)-1 -> 11
A21: Legend:
A22: Blue-outlined columns (Likelihood, Impact, Residual Likelihood, Residual Impact, Existing Controls, Treatment Plan/Type, Owner, Target Date) are the editable inputs.
A23: Inherent/Residual Rating = Likelihood x Impact (auto-calculated). Band thresholds: Low 1-5, Medium 6-10, High 11-15, Critical 16-25.
A24: Existing Controls references Control IDs from the Control Library tab (e.g. C02 = Multi-Factor Authentication).

Sheet Scoring Scale
A1: Scoring Scale
A2: Definitions used to score Likelihood and Impact across the Risk Register (1 = lowest, 5 = highest)
A4: Score | B4: Likelihood Definition | C4: Impact Definition
A5: 1 | B5: Rare — may occur only in exceptional circumstances (e.g. less than once every 5 years) | C5: Negligible — minimal disruption; no material financial or reputational impact
A6: 2 | B6: Unlikely — could occur at some point (e.g. once every 2-5 years) | C6: Minor — limited disruption; low financial impact; no external visibility
A7: 3 | B7: Possible — might occur at some point (e.g. roughly once a year) | C7: Moderate — noticeable disruption; moderate financial impact; some stakeholder or media attention
A8: 4 | B8: Likely — will probably occur (e.g. multiple times per year) | C8: Major — significant disruption; high financial impact; regulatory or senior management attention
A9: 5 | B9: Almost Certain — expected to occur, possibly frequently (e.g. monthly or more often) | C9: Severe — critical disruption to operations; severe financial/reputational impact; potential regulatory or legal action
A11: Rating bands used throughout this workbook: Inherent/Residual Rating = Likelihood x Impact.
A12: Low 1-5, Medium 6-10, High 11-15, Critical 16-25.

Sheet Control Library
A1: Control Library
A2: Reusable catalogue of controls referenced by ID in the Risk Register
A4: Control ID | B4: Control Name | C4: Category | D4: Description | E4: Effect
A5: C01 | B5: Security Awareness Training | C5: Administrative | D5: Mandatory staff training and simulated phishing exercises to reduce susceptibility to social engineering. | E5: Reduces likelihood
A6: C02 | B6: Multi-Factor Authentication (MFA) | C6: Technical | D6: MFA enforced on email, VPN, cloud administration and other critical systems. | E6: Reduces likelihood
A7: C03 | B7: Endpoint Detection & Response (EDR) | C7: Technical | D7: Automated detection, containment and response to malware and ransomware on endpoints. | E7: Reduces impact
A8: C04 | B8: Patch Management Programme | C8: Technical | D8: Scheduled vulnerability scanning and a defined SLA for patching critical systems. | E8: Reduces likelihood
A9: C05 | B9: Data Loss Prevention (DLP) | C9: Technical | D9: Monitors and blocks unauthorised transfer of sensitive data via email, web and removable media. | E9: Both
A10: C06 | B10: Cloud Security Posture Management (CSPM) | C10: Technical | D10: Continuous automated scanning of cloud environments for misconfigurations and public exposure. | E10: Reduces likelihood
A11: C07 | B11: Succession Planning & Cross-training | C11: Administrative | D11: Documented knowledge transfer and backup coverage for roles holding critical knowledge. | E11: Reduces impact
A12: C08 | B12: Business Continuity / DR Plan | C12: Administrative | D12: Documented and tested continuity plan with defined recovery time and point objectives. | E12: Reduces impact
A13: C09 | B13: Supplier Risk Assessment | C13: Administrative | D13: Due diligence, criticality rating and contingency planning for key suppliers. | E13: Both
A14: C10 | B14: Backup & Recovery Testing | C14: Technical | D14: Automated, immutable backups with scheduled restore testing to confirm recoverability. | E14: Reduces impact
A15: C11 | B15: Physical Access Control | C15: Physical | D15: Badge access, CCTV monitoring and visitor management at offices and data centres. | E15: Reduces likelihood
... A20: C16 | B20: Third-Party Due Diligence Programme | C20: Administrative | D20: Security and compliance questionnaires and risk scoring completed before vendor onboarding. | E20: Reduces likelihood

Sheet Risk Appetite
A1: Risk Appetite
A2: Statement of the level of risk the organisation is willing to accept in pursuit of its objectives
A4: The organisation has a low appetite for data breaches and regulatory non-compliance, given the potential for significant financial penalties, legal exposure and reputational harm. It has a moderate appetite for operational risk, accepting a degree of disruption where it is well controlled and does not threaten continuity of core services. It has a higher appetite for innovation-related risk, recognising that experimentation and controlled risk-taking are necessary to remain competitive and to support business growth.
A9: Appetite to Tolerance Mapping
A10: Risk Category | B10: Appetite Level | C10: Residual Rating Tolerance | D10: Escalation Trigger
A11: Data breaches / regulatory compliance | B11: Low | C11: Residual rating must be Low (1-5) | D11: Any residual rating above 6 escalated to the Board within 5 business days
A12: Operational risk | B12: Moderate | C12: Residual rating up to Medium (6-10) accepted with active monitoring | D12: Any residual rating above 12 escalated to senior management
A13: Innovation-related risk | B13: Higher | C13: Residual rating up to High (11-15) accepted to support growth initiatives | D13: Residual rating above 15 requires Executive Committee sign-off

Sheet Methodology
A1: Methodology
A2: How this risk portfolio was built
A4: Inherent vs. Residual Risk
A5: • Inherent risk is scored assuming no controls are in place; it reflects the raw likelihood and impact of the risk event.
A6: • Residual risk is scored after considering the existing controls listed in the Risk Register, reflecting the risk that remains once those controls are applied.
A7: • Both are calculated the same way (Likelihood x Impact) so they can be compared directly and the risk reduction achieved by controls is visible.
A9: Likelihood x Impact Scoring
A10: • Each risk is scored on a 1-5 scale for both Likelihood and Impact, as defined on the Scoring Scale tab.
A11: • The Rating is calculated as Likelihood x Impact, producing a score from 1 to 25.
A12: • Scores are grouped into three bands for reporting: Low (1-5), Medium (6-10), High (11-15) and Critical (16-25).
A14: How Appetite Influenced Treatment Decisions
A15: • Risks in categories where the organisation has low appetite (e.g. data breaches, regulatory compliance) were treated down to a Low residual rating wherever practicable.
... A32: • The Dashboard tab uses COUNTIFS and RANK formulas to summarise risk counts by category, by rating band, by treatment status, and to surface the top 3 risks by residual rating, with supporting bar and pie charts.

Sheet Dashboard
A1: Dashboard
A2: Portfolio summary — 15 risks across Cyber, Operational & Compliance
A4: Risks by Category | D4: Residual Risk by Rating Band
A5: Category | B5: Count | D5: Band | E5: Count
A6: Operational | B6: =COUNTIF('Risk Register'!$C$5:$C$19,A6) -> 5 | D6: Low | E6: =COUNTIF('Risk Register'!$P$5:$P$19,D6) -> 14
A7: Cyber | B7: =COUNTIF('Risk Register'!$C$5:$C$19,A7) -> 5 | D7: Medium | E7: =COUNTIF('Risk Register'!$P$5:$P$19,D7) -> 1
A8: Compliance | B8: =COUNTIF('Risk Register'!$C$5:$C$19,A8) -> 5 | D8: High | E8: =COUNTIF('Risk Register'!$P$5:$P$19,D8) -> 0
A10: Treatment Status | E10: Top 3 Risks by Residual Rating
A11: Treatment Type | B11: Count | C11: % of Total | E11: Rank | F11: ID | G11: Risk Description | H11: Residual Rating
A12: Treat | B12: =COUNTIF('Risk Register'!$I$5:$I$19,A12) -> 14 | C12: 0.93 | E12: 1 | F12: =INDEX('Risk Register'!$A$5:$A$19,MATCH(1,'Risk Register'!$Q$5:$Q$19,0)) -> R02 | G12: =INDEX('Risk Register'!$B$5:$B$19,MATCH(1,'Risk Register'!$Q$5:$Q$19,0)) -> Ransomware infection encrypts production systems, halting business operations. | H12: =INDEX('Risk Register'!$M$5:$M$19,MATCH(1,'Risk Register'!$Q$5:$Q$19,0)) -> 8
A13: Tolerate | B13: =COUNTIF('Risk Register'!$I$5:$I$19,A13) -> 1 | C13: =IFERROR(B13/SUM($B$12:$B$15),0) -> 0.066666667 | E13: 2 | F13: =INDEX('Risk Register'!$A$5:$A$19,MATCH(2,'Risk Register'!$Q$5:$Q$19,0)) -> R01 | G13: =INDEX('Risk Register'!$B$5:$B$19,MATCH(2,'Risk Register'!$Q$5:$Q$19,0)) -> Phishing attack leads to compromised employee credentials, enabling unauthorised system access. | H13: =INDEX('Risk Register'!$M$5:$M$19,MATCH(2,'Risk Register'!$Q$5:$Q$19,0)) -> 6
A14: Transfer | B14: =COUNTIF('Risk Register'!$I$5:$I$19,A14) -> 0 | C14: =IFERROR(B14/SUM($B$12:$B$15),0) -> 0 | E14: 3 | F14: =INDEX('Risk Register'!$A$5:$A$19,MATCH(3,'Risk Register'!$Q$5:$Q$19,0)) -> R03 | G14: =INDEX('Risk Register'!$B$5:$B$19,MATCH(3,'Risk Register'!$Q$5:$Q$19,0)) -> Unpatched critical vulnerabilities on internet-facing systems are exploited by threat actors. | H14: =INDEX('Risk Register'!$M$5:$M$19,MATCH(3,'Risk Register'!$Q$5:$Q$19,0)) -> 6
A15: Terminate | B15: =COUNTIF('Risk Register'!$I$5:$I$19,A15) -> 0 | C15: =IFERROR(B15/SUM($B$12:$B$15),0) -> 0

Sheet Heat Map
A1: Heat Map
A2: Inherent risk heat map — count of risks by Likelihood x Impact combination
A4: Likelihood ↓ / Impact → | B4: 1 | C4: 2 | D4: 3 | E4: 4 | F4: 5
A5: 5 | B5: =COUNTIFS('Risk Register'!$D$5:$D$19,5,'Risk Register'!$E$5:$E$19,1) -> 0 | C5: =COUNTIFS('Risk Register'!$D$5:$D$19,5,'Risk Register'!$E$5:$E$19,2) -> 0 | D5: =COUNTIFS('Risk Register'!$D$5:$D$19,5,'Risk Register'!$E$5:$E$19,3) -> 0 | E5: =COUNTIFS('Risk Register'!$D$5:$D$19,5,'Risk Register'!$E$5:$E$19,4) -> 0 | F5: =COUNTIFS('Risk Register'!$D$5:$D$19,5,'Risk Register'!$E$5:$E$19,5) -> 0
A6: 4 | B6: =COUNTIFS('Risk Register'!$D$5:$D$19,4,'Risk Register'!$E$5:$E$19,1) -> 0 | C6: =COUNTIFS('Risk Register'!$D$5:$D$19,4,'Risk Register'!$E$5:$E$19,2) -> 0 | D6: =COUNTIFS('Risk Register'!$D$5:$D$19,4,'Risk Register'!$E$5:$E$19,3) -> 0 | E6: =COUNTIFS('Risk Register'!$D$5:$D$19,4,'Risk Register'!$E$5:$E$19,4) -> 1 | F6: =COUNTIFS('Risk Register'!$D$5:$D$19,4,'Risk Register'!$E$5:$E$19,5) -> 0
A7: 3 | B7: =COUNTIFS('Risk Register'!$D$5:$D$19,3,'Risk Register'!$E$5:$E$19,1) -> 0 | C7: =COUNTIFS('Risk Register'!$D$5:$D$19,3,'Risk Register'!$E$5:$E$19,2) -> 0 | D7: =COUNTIFS('Risk Register'!$D$5:$D$19,3,'Risk Register'!$E$5:$E$19,3) -> 2 | E7: =COUNTIFS('Risk Register'!$D$5:$D$19,3,'Risk Register'!$E$5:$E$19,4) -> 3 | F7: =COUNTIFS('Risk Register'!$D$5:$D$19,3,'Risk Register'!$E$5:$E$19,5) -> 2
A8: 2 | B8: =COUNTIFS('Risk Register'!$D$5:$D$19,2,'Risk Register'!$E$5:$E$19,1) -> 0 | C8: =COUNTIFS('Risk Register'!$D$5:$D$19,2,'Risk Register'!$E$5:$E$19,2) -> 0 | D8: =COUNTIFS('Risk Register'!$D$5:$D$19,2,'Risk Register'!$E$5:$E$19,3) -> 3 | E8: =COUNTIFS('Risk Register'!$D$5:$D$19,2,'Risk Register'!$E$5:$E$19,4) -> 1 | F8: =COUNTIFS('Risk Register'!$D$5:$D$19,2,'Risk Register'!$E$5:$E$19,5) -> 3
A9: 1 | B9: =COUNTIFS('Risk Register'!$D$5:$D$19,1,'Risk Register'!$E$5:$E$19,1) -> 0 | C9: =COUNTIFS('Risk Register'!$D$5:$D$19,1,'Risk Register'!$E$5:$E$19,2) -> 0 | D9: =COUNTIFS('Risk Register'!$D$5:$D$19,1,'Risk Register'!$E$5:$E$19,3) -> 0 | E9: =COUNTIFS('Risk Register'!$D$5:$D$19,1,'Risk Register'!$E$5:$E$19,4) -> 0 | F9: =COUNTIFS('Risk Register'!$D$5:$D$19,1,'Risk Register'!$E$5:$E$19,5) -> 0
A10: Impact →
A11: Grid shows the count of risks (inherent Likelihood x Impact) from the Risk Register in each cell.
A12: Colour key: Green = Low (1-6) Amber = Medium (7-12) Red = High (13-25) Dark red (16-25)

Sheet Third-Party Register
A1: Third-Party Register
A2: Vendors and service providers with material exposure to the organisation
A4: Vendor | B4: Service | C4: Criticality | D4: Key Risks | E4: Key Controls | F4: Status
A5: AWS | B5: Cloud infrastructure hosting | C5: Critical | D5: Service outage; data breach via misconfiguration; concentration risk | E5: CSPM monitoring (C06); contractual SLAs; DR plan across regions (C08) | F5: Active
A6: Payroll Provider | B6: Outsourced payroll processing | C6: Critical | D6: Data breach of employee PII; processing errors; service disruption | E6: Vendor due diligence (C16); encrypted data transfer; SLA monitoring | F6: Active
A7: IT Managed Service Provider | B7: Helpdesk & infrastructure support | C7: High | D7: Privileged access misuse; inadequate incident response | E7: Access reviews (C11); contractual security requirements; DPIA (C12) | F7: Active
A8: Payment Processor | B8: Card payment processing | C8: Critical | D8: PCI DSS non-compliance; cardholder data exposure | E8: Network segmentation & encryption (C15); annual PCI audit | F8: Active
A9: HR SaaS Platform | B9: Core HR / people data system | C9: High | D9: Data breach of employee records; vendor lock-in | E9: DPIA on onboarding (C12); due diligence questionnaire (C16) | F9: Active
A10: Microsoft 365 | B10: Email & collaboration platform | C10: Critical | D10: Account compromise; data loss; phishing vector | E10: MFA (C02); DLP (C05); security awareness training (C01) | F10: Active
A11: External Legal Counsel | B11: Legal advisory services | C11: Medium | D11: Confidentiality breach; conflict of interest | E11: NDA in place; access limited to named matters | F11: Active
A12: Marketing Agency | B12: Digital marketing & campaign management | C12: Low | D12: Brand/reputational risk; limited data access | E12: Contractual brand guidelines; annual review | F12: Under Review
